speedtest_logger.py
speedtest_logger-0.0.9.dist-info/entry_points.txt
speedtest_logger-0.0.9.dist-info/LICENSE
speedtest_logger-0.0.9.dist-info/WHEEL
speedtest_logger-0.0.9.dist-info/METADATA
speedtest_logger-0.0.9.dist-info/RECORD
